jmx2yaml/__init__.py
jmx2yaml/cli.py
jmx2yaml/const.py
jmx2yaml/parser.py
jmx2yaml/util.py
jmx2yaml-0.1.0.dist-info/WHEEL
jmx2yaml-0.1.0.dist-info/METADATA
jmx2yaml-0.1.0.dist-info/RECORD
