Metadata-Version: 2.1
Name: jmx2yaml
Version: 0.1.0
Summary: 
Author: qiangyanwen
Author-email: 508737091@qq.com
Requires-Python: >=3.7,<4.0
Classifier: Programming Language :: Python :: 3
Classifier: Programming Language :: Python :: 3.7
Classifier: Programming Language :: Python :: 3.8
Requires-Dist: PyYAML (==5.3.1)
Requires-Dist: lxml (==4.6.2)
Requires-Dist: simplejson (==3.16.0)
